{"is_source_file": false, "format": "", "description": "", "external_files": [], "external_methods": [], "published": [], "classes": [], "methods": [], "calls": [], "search-terms": [], "state": 2, "file_id": 8, "knowledge_revision": 61, "git_revision": "ba2e6c9696f1fb95dea1e3a13475ea84dd378589", "hash": "4592f8f3865f28b577979ec09c4068d1", "format-version": 4, "code-base-name": "expense_tracker_frontend", "filename": "expense_tracker_frontend/README.md", "revision_history": [{"61": "ba2e6c9696f1fb95dea1e3a13475ea84dd378589"}]}